<?xml version="1.0" encoding="UTF-8" ?>
<pageDefinition xmlns="http://xmlns.oracle.com/adfm/uimodel" version="12.2.1.16.48" id="brokersBtfTestPagePageDef"
                Package="com.liberty.health.comms.broker.pageDefs">
    <parameters/>
    <executables>
        <variableIterator id="variables"/>
        <taskFlow id="maintaincompanyaddressbtf1"
                  taskFlowId="/WEB-INF/btf/company/maintain-company-address-btf.xml#maintain-company-address-btf"
                  activation="deferred" xmlns="http://xmlns.oracle.com/adf/controller/binding">
            <parameters>
                <parameter id="companyIdNo" value="10000061"/>
                <parameter id="countryCode" value="LS"/>
                <parameter id="addressTypeCode" value="C"/>
            </parameters>
        </taskFlow>
    </executables>
    <bindings/>
</pageDefinition>
